{
    "footer_link_portfolio": "Proyectos",
    "footer_link_consulting": "Asesoría",
    "footer_link_catalog": "Catálogo",
    "footer_link_processes": "Procesos",
    "footer_link_story": "El Taller",
    "footer_link_team": "Equipo",
    "footer_link_press": "Prensa",
    "footer_link_privacy": "Aviso Legal",
    "footer_company_description": "Excelencia contable para decisiones estratégicas.",
    "footer_nav_column_1_title": "Servicios",
    "footer_contact_title": "Contacto",
    "footer_contact_phone": "0998525994",
    "footer_contact_email": "micontableplus162026@outlook.com",
    "footer_hours_title": "Horario de Atención",
    "footer_hours_weekdays": "Lunes a Viernes",
    "footer_hours_weekdays_time": "08:00 – 18:00",
    "footer_hours_saturday": "Sábados",
    "footer_hours_saturday_time": "09:00 – 13:00",
    "footer_copyright_text": "MI CONTABLE PLUS+. TODOS LOS DERECHOS RESERVADOS."
}